pdfalive/__init__.py
pdfalive/cli.py
pdfalive/prompts.py
pdfalive/tokens.py
pdfalive/config/__init__.py
pdfalive/config/loader.py
pdfalive/config/models.py
pdfalive/models/page_content.py
pdfalive/models/rename.py
pdfalive/models/toc.py
pdfalive/processors/ocr_detection.py
pdfalive/processors/ocr_processor.py
pdfalive/processors/rename_processor.py
pdfalive/processors/toc_generator.py
pdfalive/tests/__init__.py
pdfalive/tests/test_cli.py
pdfalive/tests/test_config.py
pdfalive/tests/test_models.py
pdfalive/tests/test_tokens.py
pdfalive/tests/fixtures/__init__.py
pdfalive/tests/fixtures/example.pdf
pdfalive/tests/processors/__init__.py
pdfalive/tests/processors/test_ocr_detection.py
pdfalive/tests/processors/test_ocr_integration.py
pdfalive/tests/processors/test_ocr_processor.py
pdfalive/tests/processors/test_rename_processor.py
pdfalive/tests/processors/test_toc_generator.py
pdfalive-0.8.1.dist-info/licenses/LICENSE
pdfalive-0.8.1.dist-info/METADATA
pdfalive-0.8.1.dist-info/WHEEL
pdfalive-0.8.1.dist-info/entry_points.txt
pdfalive-0.8.1.dist-info/top_level.txt
pdfalive-0.8.1.dist-info/RECORD
