Metadata-Version: 2.4
Name: pdfalive
Version: 0.8.1
Summary: A Python library and CLI tool that uses LLMs to enhance PDF files
Author: Adam Ever-Hadani
License-Expression: MIT
Keywords: pdf,llm,toc,bookmarks,cli
Classifier: Environment :: Console
Classifier: Intended Audience :: Developers
Classifier: Programming Language :: Python :: 3
Classifier: Programming Language :: Python :: 3.13
Classifier: Topic :: Text Processing :: General
Requires-Python: <3.14,>=3.13
License-File: LICENSE
Requires-Dist: click>=8.3.1
Requires-Dist: langchain>=1.2.6
Requires-Dist: langsmith>=0.4.55
Requires-Dist: pydantic>=2.12.5
Requires-Dist: pymupdf>=1.26.6
Requires-Dist: tenacity>=9.1.0
Requires-Dist: rich>=14.0.0
Requires-Dist: urllib3>=2.6.3
Provides-Extra: anthropic
Requires-Dist: langchain-anthropic>=1.3.1; extra == "anthropic"
Provides-Extra: openai
Requires-Dist: langchain-openai>=1.1.7; extra == "openai"
Provides-Extra: ollama
Requires-Dist: ollama; extra == "ollama"
Requires-Dist: langchain-ollama>=1.0.0; extra == "ollama"
Dynamic: license-file
